setup.cfg
setup.py
src/laracrypt/__init__.py
src/laracrypt.egg-info/PKG-INFO
src/laracrypt.egg-info/SOURCES.txt
src/laracrypt.egg-info/dependency_links.txt
src/laracrypt.egg-info/requires.txt
src/laracrypt.egg-info/top_level.txt