Metadata-Version: 1.1
Name: laracrypt
Version: 1.0.0
Summary: Laravel-compatible two-way encryption
Home-page: https://github.com/serverops/laracrypt
Author: Chris Fidao
Author-email: chris@serverops.io
License: MIT
Keywords: encrypt,encryption,laravel
Platform: UNKNOWN
Classifier: License :: OSI Approved :: MIT License
Classifier: Operating System :: POSIX
Classifier: Environment :: Console
Classifier: Programming Language :: Python
Classifier: Topic :: Internet :: Proxy Servers
Classifier: Topic :: Software Development :: Libraries :: Python Modules
Classifier: Topic :: System :: Systems Administration
